dirpile.py
multifork.py
screen.py
dkrcache/Dockerfile.dkr
dkrcache/__init__.py
dkrcache/util.py
lagoon/__init__.py
lagoon/binary.py
lagoon/program.py
lagoon/scan.py
lagoon/terminal.py
lagoon/text.py
lagoon/url.py
lagoon/util.py
lagoon/sic/__init__.py
lagoon/sic/binary.py
lagoon/sic/text.py
lagoon-63.dist-info/METADATA
lagoon-63.dist-info/WHEEL
lagoon-63.dist-info/entry_points.txt
lagoon-63.dist-info/top_level.txt
lagoon-63.dist-info/RECORD
