Metadata-Version: 2.2
Name: lagoon
Version: 63
Summary: Concise layer on top of subprocess, similar to sh project
Home-page: https://pypi.org/project/lagoon/
Author: foyono
Author-email: shrovis@foyono.com
Requires-Dist: foyndation>=14
Requires-Dist: tblib>=1.7.0
Dynamic: author
Dynamic: author-email
Dynamic: description
Dynamic: description-content-type
Dynamic: home-page
Dynamic: requires-dist
Dynamic: summary
